LICENSE
README.md
setup.py
nxbinaryen/__init__.py
nxbinaryen.egg-info/PKG-INFO
nxbinaryen.egg-info/SOURCES.txt
nxbinaryen.egg-info/dependency_links.txt
nxbinaryen.egg-info/not-zip-safe
nxbinaryen.egg-info/requires.txt
nxbinaryen.egg-info/top_level.txt
nxbinaryen/capi/__init__.py
nxbinaryen/capi/api.py
nxbinaryen/capi/utils.py
nxbinaryen/enums/__init__.py
nxbinaryen/enums/expressions.py
nxbinaryen/enums/external_kinds.py
nxbinaryen/enums/features.py
nxbinaryen/enums/side_effects.py
nxbinaryen/enums/typings.py
tests/__init__.py
tests/test_kitchen_sink.py